<?xml version="1.0" encoding="utf-8"?>
<Tables xmlns:xs="http://www.w3.org/2001/XMLSchema-instance" xs:schemaLocation="https://newlifex.com https://newlifex.com/Model2022.xsd" NameSpace="VehicleVedioManage.BackManagement.Entity" ConnName="VehicleGPSVideo" Output="" BaseClass="Entity" Version="11.1.2022.0523" Document="https://newlifex.com/xcode/model" xmlns="https://newlifex.com/Model2022.xsd">
  <Table Name="AlarmConfig" Description="报警设置.报警类型设置，报警是否启用以及声音、弹窗提醒等">
    <Columns>
      <Column Name="ID" DataType="Int32" Identity="True" PrimaryKey="True" Description="报警设置主键" />
      <Column Name="Code" DataType="String" Description="编码" />
      <Column Name="Name" DataType="String" Master="True" Length="50" Description="名称" />
      <Column Name="alarmType" DataType="String" Length="100" Description="报警类型" />
      <Column Name="Enabled" DataType="Boolean" Description="启用" />
      <Column Name="soundEnabled" DataType="Boolean" Description="声音" />
      <Column Name="popupEnabled" DataType="Boolean" Description="弹窗" />
      <Column Name="alarmSource" DataType="String" Description="报警源" />
      <Column Name="statisticEnabled" DataType="Boolean" Description="统计" />
    </Columns>
    <Indexes>
      <Index Columns="Name" Unique="True" />
    </Indexes>
  </Table>
  <Table Name="JT809Command" Description="809指令。JT809指令，涉及到809转发">
    <Columns>
      <Column Name="CmdId" DataType="Int32" Identity="True" PrimaryKey="True" Description="指令编码" />
      <Column Name="SimNo" DataType="String" Description="Sim卡" />
      <Column Name="PlateNo" DataType="String" Description="车牌号" />
      <Column Name="Descr" DataType="String" Description="描述" />
      <Column Name="Cmd" DataType="Int32" Description="指令" />
      <Column Name="CmdData" DataType="String" Description="指令数据" />
      <Column Name="CreateTime" DataType="DateTime" Description="创建时间" />
      <Column Name="Status" DataType="String" />
      <Column Name="Source" DataType="String" Description="源" />
      <Column Name="PlateColor" DataType="Byte" Description="车牌颜色" />
      <Column Name="SubCmd" DataType="Int32" Description="子指令" />
      <Column Name="UserId" DataType="Int32" Description="用户编码" />
      <Column Name="Owner" DataType="String" Description="物主" Category="扩展信息"/>
      <Column Name="Remark" DataType="String" Description="备注" Category="扩展信息"/>
      <Column Name="SN" DataType="Int32" Description="序号" Category="扩展信息"/>
      <Column Name="Deleted" DataType="Boolean" Description="删除" Category="扩展信息"/>
      <Column Name="TenantId" DataType="Int32" Description="租户编码" Category="扩展信息"/>
      <Column Name="UpdateTime" DataType="DateTime" Description="更新时间" Category="扩展信息"/>
      <Column Name="GpsId" DataType="String" Description="GPS编码" Category="扩展信息"/>
      <Column Name="Data" DataType="String" Description="数据" Category="扩展信息" />
    </Columns>
    <Indexes>
      <Index Columns="PlateNo,PlateColor" Unique="True" />
      <Index Columns="SimNo" />
    </Indexes>
  </Table>
  <Table Name="ReportColumn" Description="报表列">
    <Columns>
      <Column Name="ReportColumnId" DataType="Int32" Identity="True" PrimaryKey="True" Description="报表列编码" />
      <Column Name="Name" DataType="String" Master="True" Length="50" Description="名称" />
      <Column Name="Width" DataType="Int32" Description="宽度" />
      <Column Name="Code" DataType="String" Description="编码" />
      <Column Name="No" DataType="Int32" Description="编号" />
      <Column Name="ColType" DataType="String" Description="列类型" />
      <Column Name="BasicDataCode" DataType="String" Description="基础数据编码" />
      <Column Name="CreateTime" DataType="DateTime" Description="创建时间" />
      <Column Name="Visible" DataType="Boolean" Description="显示" />
      <Column Name="Deleted" DataType="Boolean" Description="删除" />
      <Column Name="Owner" DataType="String" Description="拥有者" />
      <Column Name="ReportId" DataType="Int32" Description="报表编码" />
    </Columns>
    <Indexes>
      <Index Columns="Name" Unique="True" />
    </Indexes>
  </Table>
  <Table Name="ReportModel" Description="报表模型">
    <Columns>
      <Column Name="ReportId" DataType="Int32" Identity="True" PrimaryKey="True" Description="报表编码" />
      <Column Name="Name" DataType="String" Master="True" Description="名称" />
      <Column Name="QueryId" DataType="String" Description="查询编码" />
      <Column Name="Code" DataType="String" Description="编码" />
      <Column Name="CreateTime" DataType="DateTime" Description="创建时间" />
      <Column Name="Deleted" DataType="Boolean" Description="删除" />
      <Column Name="Owner" DataType="String" Description="拥有者" />
    </Columns>
    <Indexes>
      <Index Columns="Name" Unique="True" />
    </Indexes>
  </Table>
  <Table Name="MediaItem" Description="多媒体。多媒体信息">
    <Columns>
      <Column Name="MediaItemId" DataType="Int32" Identity="True" PrimaryKey="True" Description="多媒体项编码" />
      <Column Name="CommandId" DataType="Int32" Description="指令编码" />
      <Column Name="CommandType" DataType="String" Description="指令类型" />
      <Column Name="PlateNo" DataType="String" Description="车牌号" />
      <Column Name="SimNo" DataType="String" Description="Sim卡号" />
      <Column Name="SendTime" DataType="DateTime" Description="发送时间" />
      <Column Name="MediaDataId" DataType="Int32" Description="多媒体数据编码" />
      <Column Name="MediaType" DataType="Byte" Description="多媒体类型" />
      <Column Name="CodeFormat" DataType="Byte" Description="编码格式" />
      <Column Name="ChannelId" DataType="Byte" Description="通道编码" />
      <Column Name="EventCode" DataType="Byte" Description="事件代码" />
      <Column Name="FileName" DataType="String" Description="文件名称" />
      <Column Name="Latitude" DataType="Double" Description="纬度" />
      <Column Name="Longitude" DataType="Double" Description="经度" />
      <Column Name="Speed" DataType="Double" Description="速度" />
      <Column Name="Location" DataType="String" Description="位置" />
      <Column Name="CreateTime" DataType="DateTime" Description="创建时间"  Category="扩展信息" />
      <Column Name="TenantId" DataType="Int32" Description="租户编码" Category="扩展信息" />
      <Column Name="Deleted" DataType="Boolean" Description="删除" Category="扩展信息" />
      <Column Name="Owner" DataType="String" Length="45" Description="物主" Category="扩展信息" />
      <Column Name="Remark" DataType="String" Length="500" Description="备注" Category="扩展信息" />
      <Column Name="GPSId" DataType="String" Description="GPS编码" Category="扩展信息" />
      <Column Name="MultimediaDataId" DataType="Int32" Description="多媒体数据编码" Category="扩展信息" />
      <Column Name="MultimediaType" DataType="Byte" Description="多媒体类型" Category="扩展信息" />
      <Column Name="MultidediaCodeFormat" DataType="Byte" Description="多媒体编码格式" Category="扩展信息" />
    </Columns>
    <Indexes>
      <Index Columns="PlateNo" Unique="True" />
      <Index Columns="SendTime,PlateNo" />
      <Index Columns="SimNo" />
    </Indexes>
  </Table>
  <Table Name="MemberInfo" Description="会员信息。涉及到租赁、充值时，会员享受一定的优惠">
    <Columns>
      <Column Name="Id" DataType="Int32" Identity="True" PrimaryKey="True" Description="会员编号" />
      <Column Name="MemberType" DataType="Int16" Description="会员类型" />
      <Column Name="MemberFormNo" DataType="String" Length="16" Description="会员表单编号" />
      <Column Name="MemberTime" DataType="DateTime" Description="会员时间" />
      <Column Name="Address" DataType="String" Length="16" Description="地址" />
      <Column Name="LicenseNo" DataType="String" Description="许可编码(许可证)" />
      <Column Name="DepartmentID" DataType="String" Description="部门编码" />
      <Column Name="ContactPhone" DataType="String" Description="联系电话" />
      <Column Name="Contact" DataType="String" Description="联系人" />
      <Column Name="Name" DataType="String" Master="True" Description="名称" />
      <Column Name="Owner" DataType="String" Description="物主" Category="扩展信息" />
      <Column Name="TenantId" DataType="Int32" Description="租户编码" Category="扩展信息" />
      <Column Name="Deleted" DataType="Boolean" Description="删除" Category="扩展信息" />
      <Column Name="BankCode" DataType="String" Description="银行代码" Category="扩展信息" />
      <Column Name="BusinessScope" DataType="String" Length="200" Description="业务范围" Category="扩展信息" />
      <Column Name="Remark" DataType="String" Length="500" Description="备注" Category="扩展信息" />
      <Column Name="BankName" DataType="String" Description="银行名称" Category="扩展信息" />
      <Column Name="AccountName" DataType="String" Description="账户名" Category="扩展信息" />
      <Column Name="CreateTime" DataType="DateTime" Description="创建时间" Category="扩展信息" />
    </Columns>
    <Indexes>
      <Index Columns="Name" Unique="True" />
    </Indexes>
  </Table>
    <Table Name="PlatformInfo" Description="平台信息。主要用于转发809信号的，涉及到主链路、从链路等信息">
    <Columns>
      <Column Name="ID" DataType="Int32" Identity="True" PrimaryKey="True" Description="平台编号" />
      <Column Name="CheckEndTime" DataType="String" Description="检查结束时间" />
      <Column Name="CheckInterval" DataType="Int32" Description="检查间隔" />
      <Column Name="CheckStartTime" DataType="String" Description="检查起始时间" />
      <Column Name="MainLinkState" DataType="String" Description="主链路状态" />
      <Column Name="Name" DataType="String" Master="True" Description="平台名称" />
      <Column Name="Password" DataType="String" Description="密码" />
      <Column Name="SublinkPort" DataType="Int32" Description="从链路端口" />
      <Column Name="SublinkServerIp" DataType="String" Description="从链路IP" />
      <Column Name="SublinkState" DataType="String" Description="从链路状态" />
      <Column Name="UserId" DataType="String" Description="用户名" />
      <Column Name="CheckQuestion" DataType="String" Description="检查问题" />
      <Column Name="UpdateTime" DataType="DateTime" Description="更新时间" Category="扩展信息" />
      <Column Name="CreateTime" DataType="DateTime" Description="创建时间" Category="扩展信息" />
      <Column Name="Deleted" DataType="Byte" Description="删除" Category="扩展信息" />
      <Column Name="Owner" DataType="String" Description="拥有者" Category="扩展信息" />
      <Column Name="Remark" DataType="String" Description="备注" Category="扩展信息" />
      <Column Name="TenantId" DataType="Int32" Description="租户编码" Category="扩展信息" />
    </Columns>
      <Indexes>
        <Index Columns="Name" Unique="True" />
      </Indexes>
  </Table>
  <Table Name="DriverInfo" Description="司机信息。驾驶员基本信息">
    <Columns>
      <Column Name="DriverId" DataType="Int32" Identity="True" PrimaryKey="True" Description="司机编码" />
      <Column Name="DepartmentID" DataType="Int32" Description="部门编码" />
      <Column Name="DepartmentName" DataType="String" Description="部门名称" />
      <Column Name="DriverName" DataType="String" Description="司机姓名" />
      <Column Name="Sex" DataType="String" Description="性别" />
      <Column Name="DriverLicence" DataType="String" Description="驾驶执照" />
      <Column Name="IdentityCard" DataType="String" Description="身份证" />
      <Column Name="NativePlace" DataType="String" Description="籍贯" />
      <Column Name="Address" DataType="String" Description="地址" />
      <Column Name="Telephone" DataType="String" Description="电话" />
      <Column Name="MobilePhone" DataType="String" Description="手机号" />
      <Column Name="Birthday" DataType="DateTime" Description="生日" />
      <Column Name="DrivingType" DataType="String" Description="驾驶类型" />
      <Column Name="ExamineYear" DataType="DateTime" Description="检查年份" />
      <Column Name="Status" DataType="Int16" Description="状态" />
      <Column Name="Appointment" DataType="DateTime" Description="预约时间" />
      <Column Name="DriverRFID" DataType="String" Description="司机Sim卡" />
      <Column Name="Password" DataType="String" Description="密码" />
      <Column Name="ServiceLevel" DataType="Int32" Description="服务层级" />
      <Column Name="BgTitle" DataType="String" Description="背景标题" />
      <Column Name="Location" DataType="String" Description="位置" />
      <Column Name="PhotoFormat" DataType="String" Description="照片格式" />
      <Column Name="PhotoLength" DataType="Int32" Description="照片长度" />
      <Column Name="JobCard" DataType="String" Description="工作证" />
      <Column Name="MainDriver" DataType="Byte" Description="主驾驶员" />
      <Column Name="Owner" DataType="String" Description="物主" Category="扩展信息" />
      <Column Name="Register" DataType="DateTime" Description="注册" Category="扩展信息" />
      <Column Name="UpdateTime" DataType="DateTime" Description="更新时间" Category="扩展信息" />
      <Column Name="LicenseAgency" DataType="String" Description="许可证机构" Category="扩展信息" />
      <Column Name="CertificationDate" DataType="DateTime" Description="认证日期" Category="扩展信息" />
      <Column Name="InvalidDate" DataType="DateTime" Description="无效日期" Category="扩展信息" />
      <Column Name="Deleted" DataType="Boolean" Description="删除" Category="扩展信息" />
      <Column Name="CreateTime" DataType="DateTime" Description="创建时间" Category="扩展信息" />
      <Column Name="TenantId" DataType="Int32" Description="租户编码" Category="扩展信息" />
      <Column Name="RoyaltiesScale" DataType="Single" Description="使用规模" Category="扩展信息" />
      <Column Name="AppraisalIntegral" DataType="Single" Description="评估" Category="扩展信息" />
    <Column Name="Remark" DataType="String" Length="500" Description="备注" Category="扩展信息" />
    </Columns>
    <Indexes>
      <Index Columns="DriverName" Unique="True" />
      <Index Columns="DepartmentName" />
    </Indexes>
  </Table>
    <Table Name="SystemConfig" Description="系统配置">
    <Columns>
      <Column Name="Id" DataType="Decimal" Identity="True" PrimaryKey="True" Description="编号" />
      <Column Name="SubTitle" DataType="String" Description="副标题" />
      <Column Name="InitLat" DataType="Double" Description="初始纬度" />
      <Column Name="InitLng" DataType="Double" Description="初始经度" />
      <Column Name="InitZoomLevel" DataType="Int32" Description="初始层级" />
      <Column Name="MapType" DataType="String" Description="图商类型" />
      <Column Name="SmartKey" DataType="String" Description="图商密钥" />
      <Column Name="MaxOfflineDays" DataType="Int32" Description="最大离线天数" />
      <Column Name="DisplayStateType" DataType="String" Description="显示状态类型" />
      <Column Name="SystemTitle" DataType="String" Description="系统标题" />
      <Column Name="CheckValidateCode" DataType="String" Description="有效码" />
      <Column Name="BaiduKey" DataType="String" Description="百度Key" />
      <Column Name="AmapKey" DataType="String" Description="阿里Key" />
      <Column Name="AmapWebServiceKey" DataType="String" Description="阿里Web服务Key" />
      <Column Name="RefreshInterval" DataType="Int32" Description="刷新间隔" />
      <Column Name="AlarmInterval" DataType="Int32" Description="报警间隔" />
      <Column Name="ShowVehicleOnMap" DataType="Boolean" Description="在地图上显示车辆" />
      <Column Name="ShowDepNameOnMap" DataType="Boolean" Description="在地图上显示部门" />
      <Column Name="BaiduWebServiceKey" DataType="String"  Description="百度Web服务Key" />
      <Column Name="Deleted" DataType="Boolean" Description="删除" Category="扩展信息" />
      <Column Name="TenantId" DataType="Int32" Description="租户编码" Category="扩展信息" />
      <Column Name="Owner" DataType="String" Description="拥有者" Category="扩展信息" />
      <Column Name="Remark" DataType="String" Length="500" Description="备注" Category="扩展信息" />
      <Column Name="CreateTime" DataType="DateTime" Description="创建时间" Category="扩展信息" />
    </Columns>
  </Table>
   <Table Name="FuelTank" Description="油箱。对油箱基本信息进行管理">
    <Columns>
      <Column Name="TankId" DataType="Int32" Identity="True" PrimaryKey="True" Description="油箱编码" />
      <Column Name="TankType" DataType="String" Description="油箱类型" />
      <Column Name="VehicleId" DataType="Int32" Description="车辆编码" />
      <Column Name="TankNo" DataType="Int32" Description="油箱编号" />
      <Column Name="Width" DataType="Int32" Description="宽" />
      <Column Name="Length" DataType="Int32" Description="长" />
      <Column Name="Height" DataType="Int32" Description="高" />
      <Column Name="SensorLength" DataType="Int32" Description="传感器长度" />
      <Column Name="Capacity" DataType="Int32" Description="容量" />
      <Column Name="Radius" DataType="Int32" Description="半径" />
      <Column Name="BlindHeight" DataType="Int32" Description="盲板高度" />
      <Column Name="NormalFuelConsum" DataType="Int32" Description="正常燃料消耗" />
      <Column Name="Enable" DataType="Boolean" Description="启用" />
      <Column Name="Owner" DataType="String" Description="物主" />
      <Column Name="Remark" DataType="String" Description="备注" />
    </Columns>
     <Indexes>
       <Index Columns="VehicleId" Unique="True" />
     </Indexes>
  </Table>
  <Table Name="TerminalInfo" Description="终端信息。设备终端信息">
    <Columns>
      <Column Name="ID" DataType="Int32" Identity="True" PrimaryKey="True" Description="终端编码" />
      <Column Name="DevNo" DataType="String" Description="开发编号" />
      <Column Name="TermNo" DataType="String" Description="终端编号" />
      <Column Name="VerSoftware" DataType="Int16" Description="软件版本号" />
      <Column Name="VerHardware" DataType="Int16" Description="硬件版本号" />
      <Column Name="VerProtocol" DataType="Int16" Description="协议版本号" />
      <Column Name="MakeFactory" DataType="String" Description="制造工厂" />
      <Column Name="MakeTime" DataType="DateTime" Description="制造时间" />
      <Column Name="MakeNo" DataType="String" Description="制造编号" />
      <Column Name="State" DataType="String" Description="状态" />
      <Column Name="InstallTime" DataType="DateTime" Description="安装时间" />
      <Column Name="Waitor" DataType="String" Description="实施员" />
      <Column Name="InstallAddress" DataType="String" Description="安装地址" />
      <Column Name="UpdateTime" DataType="DateTime" Description="更新时间" />
      <Column Name="TermType" DataType="String" Description="终端类型" />
      <Column Name="SimNo" DataType="String" Description="Sim卡" />
      <Column Name="Bind" DataType="Boolean" Description="是否绑定" />
      <Column Name="Vendor" DataType="String" Description="供应商" />
      <Column Name="ModelNo" DataType="String" Description="型号" />
      <Column Name="Imei" DataType="String" Description="IMEI" />
      <Column Name="TenantId" DataType="Int32" Description="租户编码" Category="扩展信息" />
      <Column Name="CreateTime" DataType="DateTime" Description="创建时间" Category="扩展信息" />
      <Column Name="Owner" DataType="String" Description="拥有者" Category="扩展信息" />
      <Column Name="Deleted" DataType="Boolean" Description="删除" Category="扩展信息" />
      <Column Name="SeqNo" DataType="String" Description="序列号" Category="扩展信息" />
      <Column Name="CertPassword" DataType="String" Description="认证密码" Category="扩展信息" />
      <Column Name="CertString" DataType="String" Description="认证字符串" Category="扩展信息" />
      <Column Name="Reserve" DataType="String" Description="预留" Category="扩展信息" />
      <Column Name="Remark" DataType="String" Description="备注" Category="扩展信息" />
    </Columns>
  </Table>
  <Table Name="TerminalCommand" Description="终端指令">
    <Columns>
      <Column Name="CmdId" DataType="Int32" Identity="True" PrimaryKey="True" Description="指令编码" />
      <Column Name="PlateNo" DataType="String" Description="车牌号" />
      <Column Name="CmdType" DataType="Int32" Description="指令类型" />
      <Column Name="Cmd" DataType="String" Description="指令" />
      <Column Name="CmdData" DataType="String" Length="2500" Description="指令数据" />
      <Column Name="CreateDate" DataType="DateTime" Description="创建时间" />
      <Column Name="SimNo" DataType="String" Description="Sim卡" />
      <Column Name="Status" DataType="String" Description="状态" />
      <Column Name="UserId" DataType="Int32" Description="用户编码" />
      <Column Name="UpdateTime" DataType="DateTime" Description="更新时间" />
      <Column Name="VehicleId" DataType="Int32" Description="车辆编码" />
      <Column Name="Data" DataType="String" Description="数据" />
      <Column Name="SN" DataType="Int32" Description="序号" Category="扩展信息" />
      <Column Name="TenantId" DataType="Int32" Description="租户编码" Category="扩展信息" />
      <Column Name="Deleted" DataType="Boolean" Description="删除" Category="扩展信息" />
      <Column Name="Remark" DataType="String" Length="500" Description="备注" Category="扩展信息" />
      <Column Name="Owner" DataType="String" Description="拥有者" Category="扩展信息" />
    </Columns>
    <Indexes>
      <Index Columns="PlateNo" Unique="True" />
    </Indexes>
  </Table>
  <Table Name="TerminalParam" Description="终端参数">
    <Columns>
      <Column Name="ParamId" DataType="Int32" Identity="True" PrimaryKey="True" Description="参数编码" />
      <Column Name="SimNo" DataType="String" Description="Sim卡" />
      <Column Name="PlateNo" DataType="String" Description="车牌号" />
      <Column Name="Code" DataType="String" Description="代码" />
      <Column Name="Value" DataType="String" Description="值" />
      <Column Name="FieldType" DataType="String" Description="字段类型" />
      <Column Name="CreateDate" DataType="DateTime" Description="创建时间" />
      <Column Name="UpdateDate" DataType="DateTime" Description="更新时间" />
      <Column Name="Status" DataType="String" Description="状态" />
      <Column Name="CommandId" DataType="Int32" Description="指令编码" />
      <Column Name="GPSId" DataType="String" Description="GPS编码" />
      <Column Name="SN" DataType="Int32" Description="序号" Category="扩展信息" />
      <Column Name="TenantId" DataType="Int32" Description="租户编码" Category="扩展信息" />
      <Column Name="Deleted" DataType="Boolean" Description="删除" Category="扩展信息" />
      <Column Name="Owner" DataType="String" Description="拥有者" Category="扩展信息" />
      <Column Name="Remark" DataType="String" Length="500" Description="备注" Category="扩展信息" />
    </Columns>
    <Indexes>
      <Index Columns="PlateNo" Unique="True" />
      <Index Columns="SimNo"  />
    </Indexes>
  </Table>
</Tables>